./.gitignore
./.python-version
./LICENSE
./PKG-INFO
./README.md
./main.py
./pyproject.toml
./uv.lock
lizeur-0.1.3.dist-info/METADATA
lizeur-0.1.3.dist-info/WHEEL
lizeur-0.1.3.dist-info/entry_points.txt
lizeur-0.1.3.dist-info/licenses/LICENSE
lizeur-0.1.3.dist-info/RECORD
