Metadata-Version: 2.4
Name: lizeur
Version: 0.1.3
Summary: Lizeur is a MCP server to be able to get content from PDFs.
Project-URL: Homepage, https://github.com/SilverBzH/lizeur
Project-URL: Repository, https://github.com/SilverBzH/lizeur
Project-URL: Issues, https://github.com/SilverBzH/lizeur/issues
Author-email: Charlie Boutier <charlie.boutier7@gmail.com>
License: MIT
License-File: LICENSE
Keywords: ai,mcp,mistral,model-context-protocol,ocr,pdf
Classifier: Development Status :: 4 - Beta
Classifier: Intended Audience :: Developers
Classifier: License :: OSI Approved :: MIT License
Classifier: Operating System :: OS Independent
Classifier: Programming Language :: Python :: 3
Classifier: Programming Language :: Python :: 3.10
Classifier: Topic :: Scientific/Engineering :: Artificial Intelligence
Classifier: Topic :: Software Development :: Libraries :: Python Modules
Classifier: Topic :: Text Processing :: Markup
Requires-Python: >=3.10
Requires-Dist: mcp[cli]>=1.12.4
Requires-Dist: mistralai>=0.0.10
